CHANGELOG.md
LICENSE
MANIFEST.in
README.md
requirements-dev.txt
requirements.txt
setup.cfg
setup.py
dynamodb_ghost/__init__.py
dynamodb_ghost/dynamodb_ghost.py
dynamodb_ghost/utils.py
dynamodb_ghost.egg-info/PKG-INFO
dynamodb_ghost.egg-info/SOURCES.txt
dynamodb_ghost.egg-info/dependency_links.txt
dynamodb_ghost.egg-info/requires.txt
dynamodb_ghost.egg-info/top_level.txt
test/test_dynamodb_ghost.py
test/test_utils.py