Metadata-Version: 2.1
Name: dynamodb-ghost
Version: 0.0.1
Summary: Create transient, metadata-preserving copies of DynamoDB tables.
Home-page: https://github.com/TSNoble/dynamodb-ghost
Author: Tom Noble
Author-email: t.s.noble@outlook.com
License: UNKNOWN
Project-URL: Bug Reports, https://github.com/TSNoble/dynamodb-ghost/issues
Project-URL: Source, https://github.com/TSNoble/dynamodb-ghost
Keywords: aws dynamodb boto3 python
Platform: UNKNOWN
Classifier: Development Status :: 3 - Alpha
Classifier: Intended Audience :: Developers
Classifier: Topic :: Software Development :: Build Tools
Classifier: License :: OSI Approved :: MIT License
Classifier: Programming Language :: Python :: 3
Requires-Python: >=3.5
